setup.py
pynkdv/PyNKDV.py
pynkdv/__init__.py
pynkdv.egg-info/PKG-INFO
pynkdv.egg-info/SOURCES.txt
pynkdv.egg-info/dependency_links.txt
pynkdv.egg-info/requires.txt
pynkdv.egg-info/top_level.txt