Metadata-Version: 2.1
Name: pynkdv
Version: 0.0.19
Summary: for nkdv in python
Home-page: https://github.com/edisonchan2013928/PyNKDV
Author: rui
Author-email: 19251017@life.hkbu.edu.hk
